{
    "additional_titles": [
        {
            "language": "jp",
            "title": "\u3044\u3061\u3070\u3093\u3046\u3057\u308d\u306e\u5927\u9b54\u738b"
        },
        {
            "language": "pl",
            "title": "W\u0142adca Demon\u00f3w z Ostatniej \u0141awki"
        }
    ],
    "aliases": [],
    "blips": [
        {
            "blip_url": "http://blip.pl/s/61751505",
            "content": "#anime #Wiosna2010 Ichiban Ushiro no Daimaou (\u3044\u3061\u3070\u3093\u3046\u3057\u308d\u306e\u5927\u9b54\u738b) - harem, tym razem w szkole dla czarodziej\u00f3w (wi\u0119cej: http://rdir.pl/8esep)",
            "episode": 1,
            "filename": "f08ee4d906c4aa91195017fc93ddc548.jpg",
            "twitter_url": "http://twitter.com/animeblippl/status/11505807030"
        },
        {
            "blip_url": "http://blip.pl/s/65402196",
            "content": "Ichiban Ushiro no Daimaou 02 - genialny patent: Nasza Klasa w postaci ksi\u0105\u017cki (i nawet NKTalk jest!)",
            "episode": 2,
            "filename": "5c843b783d94849c17d0de85f0a7b099.jpg",
            "twitter_url": "http://twitter.com/animeblippl/status/12067038350"
        },
        {
            "blip_url": "http://blip.pl/s/67421918",
            "content": "Ichiban Ushiro no Daimaou 03 - kto\u015b by musia\u0142 Korone wyt\u0142umaczy\u0107, czemu &quot;wi\u0119kszy&quot; zazwyczaj znaczy &quot;lepszy&quot;",
            "episode": 3,
            "filename": "e3e0b0e5633bfc745d1a976b72426734.jpg",
            "twitter_url": "http://twitter.com/animeblippl/status/12490487112"
        },
        {
            "blip_url": "http://blip.pl/s/72656307",
            "content": "Ichiban Ushiro no Daimaou 05 - wielokolorowy harem, ch\u0142opiec do bicia, prywatny smok... czego chcie\u0107 wi\u0119cej od \u017cycia?",
            "episode": 5,
            "filename": "8e8be52ff06ddb2702569a5551702f47.jpg",
            "twitter_url": "http://twitter.com/animeblippl/status/13208993186"
        },
        {
            "blip_url": "http://blip.pl/s/75481083",
            "content": "Ichiban Ushiro no Daimaou 06 - Korone: dziewczyna idealna",
            "episode": 6,
            "filename": "b32e6b6bd3d25dfd5b5590ab3bf9a57d.jpg",
            "twitter_url": "http://twitter.com/animeblippl/status/13615974140"
        },
        {
            "blip_url": "http://blip.pl/s/83398007",
            "content": "Ichiban Ushiro no Daimaou 08 - odrobina tentakli jeszcze NIKOMU nie zaszkodzi\u0142a",
            "episode": 8,
            "filename": "5b3af44845a69f9cd06b17b1176c9290.jpg",
            "twitter_url": "http://twitter.com/animeblippl/status/14557025163"
        },
        {
            "blip_url": "http://blip.pl/s/89687493",
            "content": "Ichiban Ushiro no Daimaou 10 - Sai Akuto: jego poziom GARu jest znacznie powy\u017cej 9000",
            "episode": 10,
            "filename": "47d7cdf43ceafe7b1b50f0ced3c8d0ad.jpg",
            "twitter_url": "http://twitter.com/animeblippl/status/15459808907"
        },
        {
            "blip_url": "http://blip.pl/s/95378073",
            "content": "Ichiban Ushiro no Daimaou 11 - poniewa\u017c nigdy nie zapomnisz swojego pierwszego Goatse",
            "episode": 11,
            "filename": "02d03a5c2fafafcbc31b536489ae262b.jpg",
            "twitter_url": "http://twitter.com/animeblippl/status/16076315385"
        }
    ],
    "episodes": [
        {
            "date": "2010-04-02T18:30:00",
            "episode": 1,
            "score": 7.9714898103,
            "torrents": []
        },
        {
            "date": "2010-04-09T18:30:00",
            "episode": 2,
            "score": 7.9831715915,
            "torrents": []
        },
        {
            "date": "2010-04-16T18:30:00",
            "episode": 3,
            "score": 7.932552578,
            "torrents": []
        },
        {
            "date": "2010-04-23T18:30:00",
            "episode": 4,
            "score": 7.9213167828,
            "torrents": []
        },
        {
            "date": "2010-04-30T18:30:00",
            "episode": 5,
            "score": 7.9231981959,
            "torrents": []
        },
        {
            "date": "2010-05-07T18:30:00",
            "episode": 6,
            "score": 7.9345723098,
            "torrents": []
        },
        {
            "date": "2010-05-14T18:30:00",
            "episode": 7,
            "score": 7.9059927463,
            "torrents": []
        },
        {
            "date": "2010-05-21T18:30:00",
            "episode": 8,
            "score": 7.8736135853,
            "torrents": []
        },
        {
            "date": "2010-05-28T18:30:00",
            "episode": 9,
            "score": 7.8509799065,
            "torrents": []
        },
        {
            "date": "2010-06-04T18:30:00",
            "episode": 10,
            "score": 7.8439970883,
            "torrents": []
        },
        {
            "date": "2010-06-11T18:30:00",
            "episode": 11,
            "score": 7.8075341795,
            "torrents": []
        },
        {
            "date": "2010-06-18T18:30:00",
            "episode": 12,
            "score": 7.4928248554,
            "torrents": []
        }
    ],
    "episodes_count": 12,
    "episodes_length": 24,
    "external_sites": {
        "anidb": 6968,
        "ann": 11179,
        "mal": 7088,
        "schedule": null
    },
    "images": [
        {
            "description": "Yatagarasu",
            "filename": "http://s.modriv.net/abp/images/screencaps/a4ef7b9e365c460acf5a4666cfeaa997.jpg",
            "hd": false
        },
        {
            "description": "ZAJEBISTA KRESKA JEST ZAJEBISTA",
            "filename": "http://s.modriv.net/abp/images/screencaps/c87dfdeef4f8609b6b5d4b8a0c9b9b30.jpg",
            "hd": false
        },
        {
            "description": "ZAJEBISTA CENZURA JEST ZAJEBISTA",
            "filename": "http://s.modriv.net/abp/images/screencaps/5dbe2b97c4eed3b6f4caabae18d363bf.jpg",
            "hd": false
        },
        {
            "description": "Cenzura cz. 2",
            "filename": "http://s.modriv.net/abp/images/screencaps/62883b5d855f3d34c68491007f40119e.jpg",
            "hd": false
        },
        {
            "description": "Cze\u015b\u0107, Yui.",
            "filename": "http://s.modriv.net/abp/images/screencaps/7a8bc5a00a38f1d35bf96a03875f3550.jpg",
            "hd": false
        },
        {
            "description": "#anime #Wiosna2010 Ichiban Ushiro no Daimaou (\u3044\u3061\u3070\u3093\u3046\u3057\u308d\u306e\u5927\u9b54\u738b) - harem, tym razem w szkole dla czarodziej\u00f3w (wi\u0119cej: http://rdir.pl/8esep)",
            "filename": "http://s.modriv.net/abp/images/screencaps/f08ee4d906c4aa91195017fc93ddc548.jpg",
            "hd": false
        },
        {
            "description": "genialny patent: Nasza Klasa w postaci ksi\u0105\u017cki (i nawet NKTalk jest!)",
            "filename": "http://s.modriv.net/abp/images/screencaps/5c843b783d94849c17d0de85f0a7b099.jpg",
            "hd": false
        },
        {
            "description": "jiiiiiiiiiiiiiii~",
            "filename": "http://s.modriv.net/abp/images/screencaps/fab763b6cb2521adbd5fc5953c40a01f.jpg",
            "hd": false
        },
        {
            "description": "Korone is watching you pee",
            "filename": "http://s.modriv.net/abp/images/screencaps/93f9c2bde8cc0bb6ed5bbaf5222b7cae.jpg",
            "hd": false
        },
        {
            "description": "",
            "filename": "http://s.modriv.net/abp/images/screencaps/68e28f1c7f5f3976e3b730d6b9a9a741.jpg",
            "hd": false
        },
        {
            "description": "kto\u015b by musia\u0142 Korone wyt\u0142umaczy\u0107, czemu &quot;wi\u0119kszy&quot; zazwyczaj znaczy &quot;lepszy&quot;",
            "filename": "http://s.modriv.net/abp/images/screencaps/e3e0b0e5633bfc745d1a976b72426734.jpg",
            "hd": false
        },
        {
            "description": "wielokolorowy harem, ch\u0142opiec do bicia, prywatny smok... czego chcie\u0107 wi\u0119cej od \u017cycia?",
            "filename": "http://s.modriv.net/abp/images/screencaps/8e8be52ff06ddb2702569a5551702f47.jpg",
            "hd": false
        },
        {
            "description": "",
            "filename": "http://s.modriv.net/abp/images/screencaps/0da6228c639e570e8a308db64138791f.jpg",
            "hd": false
        },
        {
            "description": "",
            "filename": "http://s.modriv.net/abp/images/screencaps/61248de2481c9fcf0e9a6d513a50ac06.jpg",
            "hd": false
        },
        {
            "description": "",
            "filename": "http://s.modriv.net/abp/images/screencaps/f4f53483c88b563d5f637a69124e7e18.jpg",
            "hd": false
        },
        {
            "description": "",
            "filename": "http://s.modriv.net/abp/images/screencaps/71a557e77546d720e1283ee5839cf95f.jpg",
            "hd": false
        },
        {
            "description": "Korone: dziewczyna idealna",
            "filename": "http://s.modriv.net/abp/images/screencaps/b32e6b6bd3d25dfd5b5590ab3bf9a57d.jpg",
            "hd": false
        },
        {
            "description": "",
            "filename": "http://s.modriv.net/abp/images/screencaps/048771bacc3a01a415aba139c936ea31.jpg",
            "hd": false
        },
        {
            "description": "odrobina tentakli jeszcze NIKOMU nie zaszkodzi\u0142a",
            "filename": "http://s.modriv.net/abp/images/screencaps/5b3af44845a69f9cd06b17b1176c9290.jpg",
            "hd": false
        },
        {
            "description": "Sai Akuto: jego poziom GARu jest znacznie powy\u017cej 9000",
            "filename": "http://s.modriv.net/abp/images/screencaps/47d7cdf43ceafe7b1b50f0ced3c8d0ad.jpg",
            "hd": false
        },
        {
            "description": "poniewa\u017c nigdy nie zapomnisz swojego pierwszego Goatse",
            "filename": "http://s.modriv.net/abp/images/screencaps/02d03a5c2fafafcbc31b536489ae262b.jpg",
            "hd": false
        },
        {
            "description": "",
            "filename": "http://s.modriv.net/abp/images/screencaps/c08c6918a25621eafdd40b9959a5b5b1.jpg",
            "hd": false
        }
    ],
    "plots": [
        {
            "content": "M\u0142ody ch\u0142opak zaczyna nauk\u0119 w szkole dla czarodziej\u00f3w, po czym dowiaduje si\u0119, \u017ce gwiazdy przeznaczy\u0142y mu w przysz\u0142o\u015bci tytu\u0142 W\u0142adcy Demon\u00f3w.",
            "type": "abp"
        },
        {
            "content": "After enrolling at the Constant Magic Academy, Akuto Sai discovers he&#039;s not just a gifted student with magical powers; he&#039;s destined to become the Demon King. And though he&#039;s not that crazy about the idea, it drives the girls wild! From the sexy school girls in his class to the skin-obsessed android who&#039;s programmed to seduce him, Akuto has no shortage of wacky girl trouble. How much temptation can a demon king take?    (Source: Sentai Filmworks)",
            "type": "mal"
        },
        {
            "content": "* Based on Mizuki Shoutarou's Ichiban Ushiro no Daimaou magical fantasy romance novel series with illustrations by Itou Souichi.The story of \"love, magic, and battles\" revolves around Sai Akuto, a boy who aims to become part of his country's highest order of magicians and contribute to society as one of its clergy. On the day he is admitted into the Constan Magical Academy, his aptitude test predicts the following: \"Future Occupation ... Devil King.\" Thus begins his difficult school life in which he is resented by his studious female class head, desired by a girl with mysterious powers, and guarded by a beautiful female android.Source: ANN",
            "type": "anidb"
        },
        {
            "content": "The story of \"love, magic, and battles\" revolves around Akuto Sai, a boy who aims to become part of his country's highest order of magicians and contribute to society. On the day he is admitted into the Constant Magical Academy, his aptitude test predicts the following: \"Future Occupation \u2026 Devil King.\" Thus begins his difficult school life in which he is resented by his studious female class head, desired by a girl with mysterious powers, and guarded by a beautiful female android.",
            "type": "ann"
        }
    ],
    "ranks": [
        {
            "count": 35614,
            "date": "2012-09-29T02:46:42",
            "score": 7.45,
            "type": "mal"
        },
        {
            "count": 2524,
            "date": "2012-09-29T02:46:42",
            "score": 7.19,
            "type": "anidb"
        },
        {
            "count": 2068,
            "date": "2012-09-29T02:46:42",
            "score": 7.296,
            "type": "ann"
        }
    ],
    "season": {
        "quarter": 2,
        "year": 2010
    },
    "sequel": false,
    "sequel_parent": "",
    "title": "Ichiban Ushiro no Daimaou"
}