{
    "additional_titles": [
        {
            "language": "jp",
            "title": "\u30c6\u30ac\u30df\u30d0\u30c1 REVERSE"
        },
        {
            "language": "pl",
            "title": "Listopszczo\u0142y ODWROTNO\u015a\u0106"
        }
    ],
    "aliases": [
        "Tegami Bachi - Letter Bee REVERSE ",
        "Letter Bee Reverse ",
        "Tegami Bachi REVERSE",
        "Tegami Bachi [REVERSE] - Letter Bee"
    ],
    "blips": [
        {
            "blip_url": "http://blip.pl/s/175836862",
            "content": "#anime #Jesie\u01442010 Tegami Bachi Reverse (\u30c6\u30ac\u30df\u30d0\u30c1 REVERSE) http://rdir.pl/su7tm",
            "episode": 1,
            "filename": "84974ebb80a68c32f684cc4573cd4b27.jpg",
            "twitter_url": "http://twitter.com/animeblippl/status/26206378953"
        },
        {
            "blip_url": "http://blip.pl/s/184250427",
            "content": "Tegami Bachi Reverse 02 - nawet to #anime nie uchowa\u0142o si\u0119 przed wszechobecn\u0105 mod\u0105 na fanserwis",
            "episode": 2,
            "filename": "b07263411fac593ff475d8c2788d7178.jpg",
            "twitter_url": "http://twitter.com/animeblippl/status/26972588418"
        },
        {
            "blip_url": "http://blip.pl/s/189756767",
            "content": "Tegami Bachi Reverse 03 - znajd\u017a 10 r\u00f3\u017cnic",
            "episode": 3,
            "filename": "36784605e8274e7ad43be249a9bfd38e.jpg",
            "twitter_url": "http://twitter.com/animeblippl/status/27679172541"
        }
    ],
    "episodes": [
        {
            "date": "2010-10-02T16:55:00",
            "episode": 1,
            "score": 7.9478086957,
            "torrents": [
                {
                    "additional_info": "[1280x720 x264 AAC] ",
                    "download_count": 2,
                    "filename": "[Tamashii] Letter Bee Reverse 01[1280x720 x264 AAC] [99C8F301].mkv",
                    "group": "Tamashii",
                    "hash": "99C8F301",
                    "url": "http://www.nyaatorrents.org/?page=download&tid=163176",
                    "version": 1
                },
                {
                    "additional_info": "[1280x720 x264 AAC] ",
                    "download_count": 1,
                    "filename": "[Tamashii] Letter Bee Reverse 01v2 [1280x720 x264 AAC] [477C1699].mkv",
                    "group": "Tamashii",
                    "hash": "477C1699",
                    "url": "http://www.nyaatorrents.org/?page=download&tid=164154",
                    "version": 2
                },
                {
                    "additional_info": "[720p][H264]",
                    "download_count": 1,
                    "filename": "[Ruri]Tegami Bachi - Letter Bee REVERSE 01v2 [720p][H264][C6401B62].mkv",
                    "group": "Ruri",
                    "hash": "C6401B62",
                    "url": "http://www.nyaatorrents.org/?page=download&tid=164676",
                    "version": 2
                },
                {
                    "additional_info": "[720p][h264]",
                    "download_count": 1,
                    "filename": "[Mochi]_Letter_Bee_REVERSE_-_01_[720p][h264][427A29A0].mkv",
                    "group": "Mochi",
                    "hash": "427A29A0",
                    "url": "http://tracker.minglong.org/torrents/%5BMochi%5D_Letter_Bee_Reverse_-_01_%5B720p%5D%5Bh264%5D%5B427A29A0%5D.mkv.torrent",
                    "version": 1
                }
            ]
        },
        {
            "date": "2010-10-09T16:55:00",
            "episode": 2,
            "score": 7.9700502513,
            "torrents": [
                {
                    "additional_info": "[480p]",
                    "download_count": 1,
                    "filename": "[CrunchySubs] Tegami Bachi REVERSE - 02 [480p].mkv",
                    "group": "CrunchySubs",
                    "hash": "",
                    "url": "http://www.nyaatorrents.org/?page=download&tid=163993",
                    "version": 1
                },
                {
                    "additional_info": "[720p]",
                    "download_count": 2,
                    "filename": "[CrunchySubs] Tegami Bachi REVERSE - 02 [720p].mkv",
                    "group": "CrunchySubs",
                    "hash": "",
                    "url": "http://www.nyaatorrents.org/?page=download&tid=163997",
                    "version": 1
                },
                {
                    "additional_info": "[02]",
                    "download_count": 1,
                    "filename": "[Deep] Tegami Bachi (REVERSE) - Letter Bee - 27 (02).mkv",
                    "group": "Deep",
                    "hash": "",
                    "url": "http://www.nyaatorrents.org/?page=download&tid=164149",
                    "version": 1
                },
                {
                    "additional_info": "",
                    "download_count": 1,
                    "filename": "[WhyNot] Tegami Bachi Reverse - 02 [24205CB2].mkv",
                    "group": "WhyNot",
                    "hash": "24205CB2",
                    "url": "http://www.nyaatorrents.org/?page=torrentinfo&tid=164138",
                    "version": 1
                },
                {
                    "additional_info": "[720p][H264]",
                    "download_count": 1,
                    "filename": "[Ruri]Tegami Bachi - Letter Bee REVERSE 02 [720p][H264][A1BCF838].mkv",
                    "group": "Ruri",
                    "hash": "A1BCF838",
                    "url": "http://www.nyaatorrents.org/?page=download&tid=165501",
                    "version": 1
                }
            ]
        },
        {
            "date": "2010-10-16T16:55:00",
            "episode": 3,
            "score": 7.9922002086,
            "torrents": [
                {
                    "additional_info": "[480p]",
                    "download_count": 1,
                    "filename": "[CrunchySubs] Tegami Bachi REVERSE - 03 [480p].mkv",
                    "group": "CrunchySubs",
                    "hash": "",
                    "url": "http://www.nyaatorrents.org/?page=download&tid=165853",
                    "version": 1
                },
                {
                    "additional_info": "[720p]",
                    "download_count": 2,
                    "filename": "[CrunchySubs] Tegami Bachi REVERSE - 03 [720p].mkv",
                    "group": "CrunchySubs",
                    "hash": "",
                    "url": "http://www.nyaatorrents.org/?page=download&tid=165855",
                    "version": 1
                },
                {
                    "additional_info": "",
                    "download_count": 1,
                    "filename": "[WhyNot] Tegami Bachi Reverse - 03 [E9431AE4].mkv",
                    "group": "WhyNot",
                    "hash": "E9431AE4",
                    "url": "http://www.nyaatorrents.org/?page=torrentinfo&tid=165972",
                    "version": 1
                },
                {
                    "additional_info": "[03] ",
                    "download_count": 1,
                    "filename": "[Deep] Tegami Bachi (REVERSE) - Letter Bee - 28 (03) [07E7DAFD].mkv",
                    "group": "Deep",
                    "hash": "07E7DAFD",
                    "url": "http://www.nyaatorrents.org/?page=download&tid=166525",
                    "version": 1
                },
                {
                    "additional_info": "[720p][H264]",
                    "download_count": 1,
                    "filename": "[Ruri]Tegami Bachi - Letter Bee REVERSE 03 [720p][H264][2C05DB24].mkv",
                    "group": "Ruri",
                    "hash": "2C05DB24",
                    "url": "http://www.nyaatorrents.org/?page=download&tid=167210",
                    "version": 1
                }
            ]
        },
        {
            "date": "2010-10-23T16:55:00",
            "episode": 4,
            "score": 8.0122748815,
            "torrents": [
                {
                    "additional_info": "[720p]",
                    "download_count": 1,
                    "filename": "[CrunchySubs] Tegami Bachi REVERSE - 04 [720p].mkv",
                    "group": "CrunchySubs",
                    "hash": "",
                    "url": "http://www.nyaatorrents.org/?page=download&tid=167577",
                    "version": 1
                },
                {
                    "additional_info": "[480p]",
                    "download_count": 1,
                    "filename": "[CrunchySubs] Tegami Bachi REVERSE - 04 [480p].mkv",
                    "group": "CrunchySubs",
                    "hash": "",
                    "url": "http://www.nyaatorrents.org/?page=download&tid=167580",
                    "version": 1
                },
                {
                    "additional_info": "",
                    "download_count": 2,
                    "filename": "[WhyNot] Tegami Bachi Reverse - 04 [19F2D569].mkv",
                    "group": "WhyNot",
                    "hash": "19F2D569",
                    "url": "http://www.nyaatorrents.org/?page=torrentinfo&tid=167623",
                    "version": 1
                },
                {
                    "additional_info": "[04] ",
                    "download_count": 1,
                    "filename": "[Deep] Tegami Bachi (REVERSE) - Letter Bee - 29 (04) [5203142B].mkv",
                    "group": "Deep",
                    "hash": "5203142B",
                    "url": "http://www.nyaatorrents.org/?page=download&tid=168559",
                    "version": 1
                },
                {
                    "additional_info": "[720p][H264]",
                    "download_count": 0,
                    "filename": "[Ruri]Tegami Bachi - Letter Bee REVERSE 04 [720p][H264][BD4344D2].mkv",
                    "group": "Ruri",
                    "hash": "BD4344D2",
                    "url": "http://www.nyaatorrents.org/?page=download&tid=169610",
                    "version": 1
                }
            ]
        },
        {
            "date": "2010-10-30T16:55:00",
            "episode": 5,
            "score": 8.0119635788,
            "torrents": [
                {
                    "additional_info": "[05] ",
                    "download_count": 1,
                    "filename": "[Deep] Tegami Bachi (REVERSE) - Letter Bee - 30 (05) [49979630].mkv",
                    "group": "Deep",
                    "hash": "49979630",
                    "url": "http://www.nyaatorrents.org/?page=download&tid=169631",
                    "version": 1
                },
                {
                    "additional_info": "",
                    "download_count": 0,
                    "filename": "[WhyNot] Tegami Bachi Reverse - 05 [029B98D0].mkv",
                    "group": "WhyNot",
                    "hash": "029B98D0",
                    "url": "http://www.nyaatorrents.org/?page=download&tid=169638",
                    "version": 1
                },
                {
                    "additional_info": "[480p]",
                    "download_count": 1,
                    "filename": "[HorribleSubs] Tegami Bachi REVERSE - 30 [480p].mkv",
                    "group": "HorribleSubs",
                    "hash": "",
                    "url": "http://www.nyaatorrents.org/?page=download&tid=169843",
                    "version": 1
                },
                {
                    "additional_info": "[720p]",
                    "download_count": 1,
                    "filename": "[HorribleSubs] Tegami Bachi REVERSE - 30 [720p].mkv",
                    "group": "HorribleSubs",
                    "hash": "",
                    "url": "http://www.nyaatorrents.org/?page=download&tid=169848",
                    "version": 1
                },
                {
                    "additional_info": "[720p][H264]",
                    "download_count": 0,
                    "filename": "[Ruri]Tegami Bachi - Letter Bee REVERSE 05 [720p][H264][1125D709].mkv",
                    "group": "Ruri",
                    "hash": "1125D709",
                    "url": "http://www.nyaatorrents.org/?page=download&tid=170510",
                    "version": 1
                }
            ]
        },
        {
            "date": "2010-11-06T15:55:00",
            "episode": 6,
            "score": 8.0168140741,
            "torrents": [
                {
                    "additional_info": "[480p]",
                    "download_count": 0,
                    "filename": "[CrunchySubs] Tegami Bachi REVERSE - 06 [480p].mkv",
                    "group": "CrunchySubs",
                    "hash": "",
                    "url": "http://www.nyaatorrents.org/?page=download&tid=171279",
                    "version": 1
                },
                {
                    "additional_info": "[720p]",
                    "download_count": 1,
                    "filename": "[CrunchySubs] Tegami Bachi REVERSE - 06 [720p].mkv",
                    "group": "CrunchySubs",
                    "hash": "",
                    "url": "http://www.nyaatorrents.org/?page=download&tid=171287",
                    "version": 1
                },
                {
                    "additional_info": "[720p][H264]",
                    "download_count": 0,
                    "filename": "[OHW] Tegami Bachi - Letter Bee REVERSE 06 [720p][H264][10B364D9].mkv",
                    "group": "OHW",
                    "hash": "10B364D9",
                    "url": "http://www.nyaatorrents.org/?page=download&tid=171395",
                    "version": 1
                },
                {
                    "additional_info": "",
                    "download_count": 2,
                    "filename": "[WhyNot] Tegami Bachi Reverse - 06 [85FC5609].mkv",
                    "group": "WhyNot",
                    "hash": "85FC5609",
                    "url": "http://www.nyaatorrents.org/?page=download&tid=171446",
                    "version": 1
                },
                {
                    "additional_info": "[06] ",
                    "download_count": 1,
                    "filename": "[Deep] Tegami Bachi (REVERSE) - Letter Bee - 31 (06) [3CF00BEB].mkv",
                    "group": "Deep",
                    "hash": "3CF00BEB",
                    "url": "http://www.nyaatorrents.org/?page=download&tid=171483",
                    "version": 1
                }
            ]
        },
        {
            "date": "2010-11-13T15:55:00",
            "episode": 7,
            "score": 8.0359756944,
            "torrents": []
        },
        {
            "date": "2010-11-20T15:55:00",
            "episode": 8,
            "score": 8.0451070496,
            "torrents": []
        },
        {
            "date": "2010-11-27T15:55:00",
            "episode": 9,
            "score": 8.0544255051,
            "torrents": [
                {
                    "additional_info": "",
                    "download_count": 2,
                    "filename": "[WhyNot] Tegami Bachi Reverse - 09 [1B06D148].mkv",
                    "group": "WhyNot",
                    "hash": "1B06D148",
                    "url": "http://www.nyaatorrents.org/?page=download&tid=178106",
                    "version": 1
                },
                {
                    "additional_info": "[720p][H264]",
                    "download_count": 1,
                    "filename": "[Ruri]Tegami Bachi - Letter Bee REVERSE 09 [720p][H264][C7F14B4F].mkv",
                    "group": "Ruri",
                    "hash": "C7F14B4F",
                    "url": "http://www.nyaatorrents.org/?page=download&tid=178380",
                    "version": 1
                }
            ]
        },
        {
            "date": "2010-12-04T15:55:00",
            "episode": 10,
            "score": 8.0496555891,
            "torrents": [
                {
                    "additional_info": "[480p]",
                    "download_count": 1,
                    "filename": "[CrunchySubs] Tegami Bachi REVERSE - 10 [480p].mkv",
                    "group": "CrunchySubs",
                    "hash": "",
                    "url": "http://www.nyaatorrents.org/?page=download&tid=177790",
                    "version": 1
                },
                {
                    "additional_info": "[720p]",
                    "download_count": 0,
                    "filename": "[CrunchySubs] Tegami Bachi REVERSE - 10 [720p].mkv",
                    "group": "CrunchySubs",
                    "hash": "",
                    "url": "http://www.nyaatorrents.org/?page=download&tid=177791",
                    "version": 1
                },
                {
                    "additional_info": "[720p][H264]",
                    "download_count": 0,
                    "filename": "[Ruri]Tegami Bachi - Letter Bee REVERSE 10 [720p][H264][99BFA6BC].mkv",
                    "group": "Ruri",
                    "hash": "99BFA6BC",
                    "url": "http://www.nyaatorrents.org/?page=download&tid=180143",
                    "version": 1
                },
                {
                    "additional_info": "",
                    "download_count": 1,
                    "filename": "[WhyNot] Tegami Bachi Reverse - 10 [4DD73D65].mkv",
                    "group": "WhyNot",
                    "hash": "4DD73D65",
                    "url": "http://www.nyaatorrents.org/?page=torrentinfo&tid=181780",
                    "version": 1
                }
            ]
        },
        {
            "date": "2010-12-11T15:55:00",
            "episode": 11,
            "score": 8.0604435484,
            "torrents": [
                {
                    "additional_info": "[480p]",
                    "download_count": 0,
                    "filename": "[CrunchySubs] Tegami Bachi REVERSE - 11 [480p].mkv",
                    "group": "CrunchySubs",
                    "hash": "",
                    "url": "http://www.nyaatorrents.org/?page=download&tid=179267",
                    "version": 1
                },
                {
                    "additional_info": "[720p]",
                    "download_count": 1,
                    "filename": "[CrunchySubs] Tegami Bachi REVERSE - 11 [720p].mkv",
                    "group": "CrunchySubs",
                    "hash": "",
                    "url": "http://www.nyaatorrents.org/?page=download&tid=179268",
                    "version": 1
                },
                {
                    "additional_info": "[720p][H264]",
                    "download_count": 0,
                    "filename": "[Ruri]Tegami Bachi - Letter Bee REVERSE 11 [720p][H264][259F8DDF].mkv",
                    "group": "Ruri",
                    "hash": "259F8DDF",
                    "url": "http://www.nyaatorrents.org/?page=download&tid=180983",
                    "version": 1
                }
            ]
        },
        {
            "date": "2010-12-18T15:55:00",
            "episode": 12,
            "score": 8.0690338983,
            "torrents": [
                {
                    "additional_info": "[480p]",
                    "download_count": 0,
                    "filename": "[CrunchySubs] Tegami Bachi REVERSE - 12 [480p].mkv",
                    "group": "CrunchySubs",
                    "hash": "",
                    "url": "http://www.nyaatorrents.org/?page=download&tid=181334",
                    "version": 1
                },
                {
                    "additional_info": "[720p]",
                    "download_count": 1,
                    "filename": "[CrunchySubs] Tegami Bachi REVERSE - 12 [720p].mkv",
                    "group": "CrunchySubs",
                    "hash": "",
                    "url": "http://www.nyaatorrents.org/?page=download&tid=181335",
                    "version": 1
                },
                {
                    "additional_info": "[720p][H264]",
                    "download_count": 0,
                    "filename": "[Ruri]Tegami Bachi - Letter Bee REVERSE 12 [720p][H264][4EBA893D].mkv",
                    "group": "Ruri",
                    "hash": "4EBA893D",
                    "url": "http://www.nyaatorrents.org/?page=download&tid=183017",
                    "version": 1
                }
            ]
        },
        {
            "date": "2010-12-25T15:55:00",
            "episode": 13,
            "score": 0.0,
            "torrents": [
                {
                    "additional_info": "[480p]",
                    "download_count": 1,
                    "filename": "[CrunchySubs] Tegami Bachi REVERSE - 13 [480p].mkv",
                    "group": "CrunchySubs",
                    "hash": "",
                    "url": "http://www.nyaatorrents.org/?page=download&tid=182146",
                    "version": 1
                },
                {
                    "additional_info": "[720p]",
                    "download_count": 2,
                    "filename": "[CrunchySubs] Tegami Bachi REVERSE - 13 [720p].mkv",
                    "group": "CrunchySubs",
                    "hash": "",
                    "url": "http://www.nyaatorrents.org/?page=download&tid=182148",
                    "version": 1
                },
                {
                    "additional_info": "[720p][H264]",
                    "download_count": 1,
                    "filename": "[Ruri]Tegami Bachi - Letter Bee REVERSE 13 [720p][H264][4EFEFFFA].mkv",
                    "group": "Ruri",
                    "hash": "4EFEFFFA",
                    "url": "http://www.nyaatorrents.org/?page=download&tid=185345",
                    "version": 1
                }
            ]
        },
        {
            "date": "2011-01-08T15:55:00",
            "episode": 14,
            "score": 0.0,
            "torrents": [
                {
                    "additional_info": "[480p]",
                    "download_count": 0,
                    "filename": "[CrunchySubs] Tegami Bachi REVERSE - 14 [480p].mkv",
                    "group": "CrunchySubs",
                    "hash": "",
                    "url": "http://www.nyaatorrents.org/?page=download&tid=185219",
                    "version": 1
                },
                {
                    "additional_info": "[720p]",
                    "download_count": 1,
                    "filename": "[CrunchySubs] Tegami Bachi REVERSE - 14 [720p].mkv",
                    "group": "CrunchySubs",
                    "hash": "",
                    "url": "http://www.nyaatorrents.org/?page=download&tid=185241",
                    "version": 1
                },
                {
                    "additional_info": "[720p][H264]",
                    "download_count": 0,
                    "filename": "[Ruri]Tegami Bachi - Letter Bee REVERSE 14 [720p][H264][92242E57].mkv",
                    "group": "Ruri",
                    "hash": "92242E57",
                    "url": "http://www.nyaatorrents.org/?page=download&tid=187793",
                    "version": 1
                }
            ]
        },
        {
            "date": "2011-01-15T15:55:00",
            "episode": 15,
            "score": 0.0,
            "torrents": [
                {
                    "additional_info": "[480p]",
                    "download_count": 1,
                    "filename": "[CrunchySubs] Tegami Bachi REVERSE - 15 [480p].mkv",
                    "group": "CrunchySubs",
                    "hash": "",
                    "url": "http://www.nyaatorrents.org/?page=download&tid=186455",
                    "version": 1
                },
                {
                    "additional_info": "[720p]",
                    "download_count": 2,
                    "filename": "[CrunchySubs] Tegami Bachi REVERSE - 15 [720p].mkv",
                    "group": "CrunchySubs",
                    "hash": "",
                    "url": "http://www.nyaatorrents.org/?page=download&tid=186456",
                    "version": 1
                },
                {
                    "additional_info": "[720p][H264]",
                    "download_count": 1,
                    "filename": "[Ruri]Tegami Bachi - Letter Bee REVERSE 15 [720p][H264][8D63FE17].mkv",
                    "group": "Ruri",
                    "hash": "8D63FE17",
                    "url": "http://www.nyaatorrents.org/?page=download&tid=189142",
                    "version": 1
                }
            ]
        },
        {
            "date": "2011-01-22T15:55:00",
            "episode": 16,
            "score": 0.0,
            "torrents": [
                {
                    "additional_info": "[720p]",
                    "download_count": 1,
                    "filename": "[CrunchySubs] Tegami Bachi REVERSE - 16 [720p].mkv",
                    "group": "CrunchySubs",
                    "hash": "",
                    "url": "http://www.nyaatorrents.org/?page=download&tid=188079",
                    "version": 1
                },
                {
                    "additional_info": "[720p][H264]",
                    "download_count": 0,
                    "filename": "[Ruri]Tegami Bachi - Letter Bee REVERSE 16 [720p][H264][7E8A87E5].mkv",
                    "group": "Ruri",
                    "hash": "7E8A87E5",
                    "url": "http://www.nyaatorrents.org/?page=download&tid=190924",
                    "version": 1
                }
            ]
        },
        {
            "date": "2011-01-29T15:55:00",
            "episode": 17,
            "score": 0.0,
            "torrents": [
                {
                    "additional_info": "[480p]",
                    "download_count": 0,
                    "filename": "[CrunchySubs] Tegami Bachi REVERSE - 17 [480p].mkv",
                    "group": "CrunchySubs",
                    "hash": "",
                    "url": "http://www.nyaatorrents.org/?page=download&tid=190074",
                    "version": 1
                },
                {
                    "additional_info": "[720p]",
                    "download_count": 2,
                    "filename": "[CrunchySubs] Tegami Bachi REVERSE - 17 [720p].mkv",
                    "group": "CrunchySubs",
                    "hash": "",
                    "url": "http://www.nyaatorrents.org/?page=download&tid=190077",
                    "version": 1
                },
                {
                    "additional_info": "[720p][H264]",
                    "download_count": 0,
                    "filename": "[Ruri]Tegami Bachi - Letter Bee REVERSE 17 [720p][H264][99886289].mkv",
                    "group": "Ruri",
                    "hash": "99886289",
                    "url": "http://www.nyaatorrents.org/?page=download&tid=191675",
                    "version": 1
                }
            ]
        },
        {
            "date": "2011-02-05T15:55:00",
            "episode": 18,
            "score": 8.118152039,
            "torrents": [
                {
                    "additional_info": "[480p]",
                    "download_count": 1,
                    "filename": "[CrunchySubs] Tegami Bachi REVERSE - 18 [480p].mkv",
                    "group": "CrunchySubs",
                    "hash": "",
                    "url": "http://www.nyaa.eu/?page=download&tid=193516",
                    "version": 1
                },
                {
                    "additional_info": "[720p]",
                    "download_count": 1,
                    "filename": "[CrunchySubs] Tegami Bachi REVERSE - 18 [720p].mkv",
                    "group": "CrunchySubs",
                    "hash": "",
                    "url": "http://www.nyaa.eu/?page=download&tid=193517",
                    "version": 1
                },
                {
                    "additional_info": "[720p][H264]",
                    "download_count": 0,
                    "filename": "[Ruri]Tegami Bachi - Letter Bee REVERSE 18 [720p][H264][715327CE].mkv",
                    "group": "Ruri",
                    "hash": "715327CE",
                    "url": "http://www.nyaa.eu/?page=download&tid=193784",
                    "version": 1
                }
            ]
        },
        {
            "date": "2011-02-12T15:55:00",
            "episode": 19,
            "score": 8.1253031869,
            "torrents": [
                {
                    "additional_info": "[480p]",
                    "download_count": 1,
                    "filename": "[CrunchySubs] Tegami Bachi REVERSE - 19 [480p].mkv",
                    "group": "CrunchySubs",
                    "hash": "",
                    "url": "http://www.nyaa.eu/?page=download&tid=193519",
                    "version": 1
                },
                {
                    "additional_info": "[720p]",
                    "download_count": 2,
                    "filename": "[CrunchySubs] Tegami Bachi REVERSE - 19 [720p].mkv",
                    "group": "CrunchySubs",
                    "hash": "",
                    "url": "http://www.nyaa.eu/?page=download&tid=193520",
                    "version": 1
                },
                {
                    "additional_info": "[720p][H264]",
                    "download_count": 0,
                    "filename": "[Ruri]Tegami Bachi - Letter Bee REVERSE 19 [720p][H264][EEFEAEFE].mkv",
                    "group": "Ruri",
                    "hash": "EEFEAEFE",
                    "url": "http://www.nyaa.eu/?page=download&tid=194674",
                    "version": 1
                }
            ]
        },
        {
            "date": "2011-02-19T15:55:00",
            "episode": 20,
            "score": 8.1156008439,
            "torrents": [
                {
                    "additional_info": "[720p][H264]",
                    "download_count": 0,
                    "filename": "[Ruri]Tegami Bachi - Letter Bee REVERSE 20 [720p][H264][BDE62EB2].mkv",
                    "group": "Ruri",
                    "hash": "BDE62EB2",
                    "url": "http://www.nyaa.eu/?page=download&tid=197320",
                    "version": 1
                },
                {
                    "additional_info": "[720p]",
                    "download_count": 0,
                    "filename": "[CrunchySubs] Tegami Bachi REVERSE - 20 [720p].mkv",
                    "group": "CrunchySubs",
                    "hash": "",
                    "url": "http://www.nyaa.eu/?page=download&tid=207797",
                    "version": 1
                }
            ]
        },
        {
            "date": "2011-02-26T15:55:00",
            "episode": 21,
            "score": 8.1145022606,
            "torrents": [
                {
                    "additional_info": "[720p][H264]",
                    "download_count": 0,
                    "filename": "[Ruri]Tegami Bachi - Letter Bee REVERSE 21 [720p][H264][411E10EC].mkv",
                    "group": "Ruri",
                    "hash": "411E10EC",
                    "url": "http://www.nyaa.eu/?page=download&tid=199398",
                    "version": 1
                },
                {
                    "additional_info": "[720p]",
                    "download_count": 1,
                    "filename": "[CrunchySubs] Tegami Bachi REVERSE - 21 [720p].mkv",
                    "group": "CrunchySubs",
                    "hash": "",
                    "url": "http://www.nyaa.eu/?page=download&tid=207802",
                    "version": 1
                }
            ]
        },
        {
            "date": "2011-03-05T15:55:00",
            "episode": 22,
            "score": 8.1317951807,
            "torrents": [
                {
                    "additional_info": "[720p][H264]",
                    "download_count": 0,
                    "filename": "[Ruri]Tegami Bachi - Letter Bee REVERSE 22 [720p][H264][ACC49784].mkv",
                    "group": "Ruri",
                    "hash": "ACC49784",
                    "url": "http://www.nyaa.eu/?page=download&tid=199400",
                    "version": 1
                },
                {
                    "additional_info": "[720p]",
                    "download_count": 1,
                    "filename": "[CrunchySubs] Tegami Bachi REVERSE - 22 [720p].mkv",
                    "group": "CrunchySubs",
                    "hash": "",
                    "url": "http://www.nyaa.eu/?page=download&tid=207805",
                    "version": 1
                }
            ]
        },
        {
            "date": "2011-03-12T15:55:00",
            "episode": 23,
            "score": 8.1290972763,
            "torrents": [
                {
                    "additional_info": "[480p]",
                    "download_count": 1,
                    "filename": "[FUNiGuys] Tegami Bachi REVERSE - 23 [480p].mkv",
                    "group": "FUNiGuys",
                    "hash": "",
                    "url": "http://www.nyaa.eu/?page=download&tid=199886",
                    "version": 1
                },
                {
                    "additional_info": "[720p]",
                    "download_count": 1,
                    "filename": "[FUNiGuys] Tegami Bachi REVERSE - 23 [720p].mkv",
                    "group": "FUNiGuys",
                    "hash": "",
                    "url": "http://www.nyaa.eu/?page=download&tid=199898",
                    "version": 1
                },
                {
                    "additional_info": "[720p][H264]",
                    "download_count": 1,
                    "filename": "[Ruri]Tegami Bachi - Letter Bee REVERSE 23 [720p][H264][FBF9E1DB].mkv",
                    "group": "Ruri",
                    "hash": "FBF9E1DB",
                    "url": "http://www.nyaa.eu/?page=download&tid=201884",
                    "version": 1
                },
                {
                    "additional_info": "[720p]",
                    "download_count": 1,
                    "filename": "[CrunchySubs] Tegami Bachi REVERSE - 23 [720p].mkv",
                    "group": "CrunchySubs",
                    "hash": "",
                    "url": "http://www.nyaa.eu/?page=download&tid=207812",
                    "version": 1
                }
            ]
        },
        {
            "date": "2011-03-19T15:55:00",
            "episode": 24,
            "score": 8.1296563574,
            "torrents": [
                {
                    "additional_info": "[720p][H264]",
                    "download_count": 1,
                    "filename": "[Ruri]Tegami Bachi - Letter Bee REVERSE 24 [720p][H264][0E5F36AE].mkv",
                    "group": "Ruri",
                    "hash": "0E5F36AE",
                    "url": "http://www.nyaa.eu/?page=download&tid=203893",
                    "version": 1
                },
                {
                    "additional_info": "[720p]",
                    "download_count": 0,
                    "filename": "[CrunchySubs] Tegami Bachi REVERSE - 24 [720p].mkv",
                    "group": "CrunchySubs",
                    "hash": "",
                    "url": "http://www.nyaa.eu/?page=download&tid=207820",
                    "version": 1
                }
            ]
        },
        {
            "date": "2011-03-26T15:55:00",
            "episode": 25,
            "score": 8.0753341655,
            "torrents": [
                {
                    "additional_info": "[720p][H264]",
                    "download_count": 1,
                    "filename": "[Ruri]Tegami Bachi - Letter Bee REVERSE 25 [720p][H264][FA32494D].mkv",
                    "group": "Ruri",
                    "hash": "FA32494D",
                    "url": "http://www.nyaa.eu/?page=download&tid=203895",
                    "version": 1
                },
                {
                    "additional_info": "[720p]",
                    "download_count": 1,
                    "filename": "[CrunchySubs] Tegami Bachi REVERSE - 25 [720p].mkv",
                    "group": "CrunchySubs",
                    "hash": "",
                    "url": "http://www.nyaa.eu/?page=download&tid=207823",
                    "version": 1
                }
            ]
        }
    ],
    "episodes_count": 25,
    "episodes_length": 24,
    "external_sites": {
        "anidb": 7458,
        "ann": 11600,
        "mal": 8311,
        "schedule": null
    },
    "images": [
        {
            "description": "",
            "filename": "http://s.modriv.net/abp/images/screencaps/8d28b816e6731af5a6827cc8c4ca0aec.jpg",
            "hd": false
        },
        {
            "description": "",
            "filename": "http://s.modriv.net/abp/images/screencaps/bcb3c154e1e281c1ecd7538791b21574.jpg",
            "hd": false
        },
        {
            "description": "W tym anime wszyscy p\u0142acz\u0105 rzewnymi \u0142zami",
            "filename": "http://s.modriv.net/abp/images/screencaps/e9f599f2bdcfc87d054cf96ffe1a47ff.jpg",
            "hd": false
        },
        {
            "description": "...bez wyj\u0105tku",
            "filename": "http://s.modriv.net/abp/images/screencaps/cb513c5d307d4cd3893c09e119ad2527.jpg",
            "hd": false
        },
        {
            "description": "A mo\u017ce po\u0144czochy?",
            "filename": "http://s.modriv.net/abp/images/screencaps/d424807e07d1776faeacd30df1fe1732.jpg",
            "hd": false
        },
        {
            "description": "#anime #Jesie\u01442010 Tegami Bachi Reverse (\u30c6\u30ac\u30df\u30d0\u30c1 REVERSE) http://rdir.pl/su7tm",
            "filename": "http://s.modriv.net/abp/images/screencaps/84974ebb80a68c32f684cc4573cd4b27.jpg",
            "hd": false
        },
        {
            "description": "",
            "filename": "http://s.modriv.net/abp/images/screencaps/2f5be1222512a37779ff8e6a3ede185b.jpg",
            "hd": false
        },
        {
            "description": "",
            "filename": "http://s.modriv.net/abp/images/screencaps/c517422b6d0f60504eb9267a7d8395da.jpg",
            "hd": false
        },
        {
            "description": "",
            "filename": "http://s.modriv.net/abp/images/screencaps/e0bfdf93f4d1b65c5a5ff8dbf2efaceb.jpg",
            "hd": false
        },
        {
            "description": "",
            "filename": "http://s.modriv.net/abp/images/screencaps/5fb594823f514a79cd7d670e6a777229.jpg",
            "hd": false
        },
        {
            "description": "nawet to #anime nie uchowa\u0142o si\u0119 przed wszechobecn\u0105 mod\u0105 na fanserwis",
            "filename": "http://s.modriv.net/abp/images/screencaps/b07263411fac593ff475d8c2788d7178.jpg",
            "hd": false
        },
        {
            "description": "",
            "filename": "http://s.modriv.net/abp/images/screencaps/adfd549097e2482baf2460e6ecb00a07.jpg",
            "hd": false
        },
        {
            "description": "znajd\u017a 10 r\u00f3\u017cnic",
            "filename": "http://s.modriv.net/abp/images/screencaps/36784605e8274e7ad43be249a9bfd38e.jpg",
            "hd": false
        },
        {
            "description": "",
            "filename": "http://s.modriv.net/abp/images/screencaps/184a4b01e8a2820589c2439aefd356f4.jpg",
            "hd": false
        },
        {
            "description": "",
            "filename": "http://s.modriv.net/abp/images/screencaps/b5fd4ebb065ece39acdc3b8f89b40bba.jpg",
            "hd": false
        }
    ],
    "plots": [
        {
            "content": "Kontynuacja przyg\u00f3d m\u0142odego dor\u0119czyciela list\u00f3w i jego przyjaci\u00f3\u0142.",
            "type": "abp"
        }
    ],
    "ranks": [
        {
            "count": 7332,
            "date": "2012-09-29T12:53:37",
            "score": 8.02,
            "type": "mal"
        },
        {
            "count": 494,
            "date": "2012-09-29T12:53:37",
            "score": 7.59,
            "type": "anidb"
        },
        {
            "count": 393,
            "date": "2012-09-29T12:53:37",
            "score": 7.951,
            "type": "ann"
        }
    ],
    "season": {
        "quarter": 4,
        "year": 2010
    },
    "sequel": true,
    "sequel_parent": "45",
    "title": "Tegami Bachi Reverse"
}