{
    "additional_titles": [
        {
            "language": "jp",
            "title": "\u6ce2\u6253\u969b\u306e\u3080\u308d\u307f\u3055\u3093"
        },
        {
            "language": "pl",
            "title": "Muromi Falistowielokraw\u0119dziowa"
        }
    ],
    "aliases": [
        "Namiuchigiwa no Muromi-san"
    ],
    "blips": [],
    "episodes": [
        {
            "date": "2013-04-06T18:15:00",
            "episode": 1,
            "score": 6.8739248434,
            "torrents": [
                {
                    "additional_info": "[720p]",
                    "download_count": 13,
                    "filename": "[HorribleSubs] Namiuchigiwa no Muromi-san - 01 [720p].mkv",
                    "group": "HorribleSubs",
                    "hash": "",
                    "url": "http://www.nyaa.eu/?page=download&tid=420882",
                    "version": 1
                },
                {
                    "additional_info": "[480p]",
                    "download_count": 1,
                    "filename": "[HorribleSubs] Namiuchigiwa no Muromi-san - 01 [480p].mkv",
                    "group": "HorribleSubs",
                    "hash": "",
                    "url": "http://www.nyaa.eu/?page=download&tid=420883",
                    "version": 1
                },
                {
                    "additional_info": "[1080p]",
                    "download_count": 3,
                    "filename": "[HorribleSubs] Namiuchigiwa no Muromi-san - 01 [1080p].mkv",
                    "group": "HorribleSubs",
                    "hash": "",
                    "url": "http://www.nyaa.eu/?page=download&tid=420885",
                    "version": 1
                },
                {
                    "additional_info": "",
                    "download_count": 3,
                    "filename": "[Vivid] Namiuchigiwa no Muromi-san - 01 [04AAE0FA].mkv",
                    "group": "Vivid",
                    "hash": "04AAE0FA",
                    "url": "http://www.nyaa.eu/?page=download&tid=421040",
                    "version": 1
                },
                {
                    "additional_info": "",
                    "download_count": 0,
                    "filename": "[Diogo4D-Scylla] Namiuchigiwa no Muromi-san 01 [59EEE8D5].mkv",
                    "group": "Diogo4D-Scylla",
                    "hash": "59EEE8D5",
                    "url": "http://www.nyaa.eu/?page=download&tid=422993",
                    "version": 1
                }
            ]
        },
        {
            "date": "2013-04-13T18:15:00",
            "episode": 2,
            "score": 6.9166071429,
            "torrents": [
                {
                    "additional_info": "[480p]",
                    "download_count": 1,
                    "filename": "[HorribleSubs] Namiuchigiwa no Muromi-san - 02 [480p].mkv",
                    "group": "HorribleSubs",
                    "hash": "",
                    "url": "http://www.nyaa.eu/?page=download&tid=423293",
                    "version": 1
                },
                {
                    "additional_info": "[720p]",
                    "download_count": 8,
                    "filename": "[HorribleSubs] Namiuchigiwa no Muromi-san - 02 [720p].mkv",
                    "group": "HorribleSubs",
                    "hash": "",
                    "url": "http://www.nyaa.eu/?page=download&tid=423294",
                    "version": 1
                },
                {
                    "additional_info": "[1080p]",
                    "download_count": 2,
                    "filename": "[HorribleSubs] Namiuchigiwa no Muromi-san - 02 [1080p].mkv",
                    "group": "HorribleSubs",
                    "hash": "",
                    "url": "http://www.nyaa.eu/?page=download&tid=423298",
                    "version": 1
                },
                {
                    "additional_info": "",
                    "download_count": 2,
                    "filename": "[Vivid] Namiuchigiwa no Muromi-san - 02 [7C0E4A33].mkv",
                    "group": "Vivid",
                    "hash": "7C0E4A33",
                    "url": "http://www.nyaa.eu/?page=download&tid=423441",
                    "version": 1
                }
            ]
        },
        {
            "date": "2013-04-20T18:15:00",
            "episode": 3,
            "score": 6.9567256637,
            "torrents": [
                {
                    "additional_info": "[480p]",
                    "download_count": 3,
                    "filename": "[HorribleSubs] Namiuchigiwa no Muromi-san - 03 [480p].mkv",
                    "group": "HorribleSubs",
                    "hash": "",
                    "url": "http://www.nyaa.eu/?page=download&tid=425591",
                    "version": 1
                },
                {
                    "additional_info": "[1080p]",
                    "download_count": 4,
                    "filename": "[HorribleSubs] Namiuchigiwa no Muromi-san - 03 [1080p].mkv",
                    "group": "HorribleSubs",
                    "hash": "",
                    "url": "http://www.nyaa.eu/?page=download&tid=425592",
                    "version": 1
                },
                {
                    "additional_info": "[720p]",
                    "download_count": 9,
                    "filename": "[HorribleSubs] Namiuchigiwa no Muromi-san - 03 [720p].mkv",
                    "group": "HorribleSubs",
                    "hash": "",
                    "url": "http://www.nyaa.eu/?page=download&tid=425593",
                    "version": 1
                },
                {
                    "additional_info": "",
                    "download_count": 2,
                    "filename": "[Vivid] Namiuchigiwa no Muromi-san - 03 [350D54D3].mkv",
                    "group": "Vivid",
                    "hash": "350D54D3",
                    "url": "http://www.nyaa.eu/?page=download&tid=425759",
                    "version": 1
                }
            ]
        },
        {
            "date": "2013-04-27T18:15:00",
            "episode": 4,
            "score": 6.9422016349,
            "torrents": [
                {
                    "additional_info": "[480p]",
                    "download_count": 1,
                    "filename": "[HorribleSubs] Namiuchigiwa no Muromi-san - 04 [480p].mkv",
                    "group": "HorribleSubs",
                    "hash": "",
                    "url": "http://www.nyaa.eu/?page=download&tid=427968",
                    "version": 1
                },
                {
                    "additional_info": "[720p]",
                    "download_count": 6,
                    "filename": "[HorribleSubs] Namiuchigiwa no Muromi-san - 04 [720p].mkv",
                    "group": "HorribleSubs",
                    "hash": "",
                    "url": "http://www.nyaa.eu/?page=download&tid=427969",
                    "version": 1
                },
                {
                    "additional_info": "[1080p]",
                    "download_count": 2,
                    "filename": "[HorribleSubs] Namiuchigiwa no Muromi-san - 04 [1080p].mkv",
                    "group": "HorribleSubs",
                    "hash": "",
                    "url": "http://www.nyaa.eu/?page=download&tid=427970",
                    "version": 1
                },
                {
                    "additional_info": "",
                    "download_count": 1,
                    "filename": "[Vivid] Namiuchigiwa no Muromi-san - 04 [B5904569].mkv",
                    "group": "Vivid",
                    "hash": "B5904569",
                    "url": "http://www.nyaa.eu/?page=download&tid=428127",
                    "version": 1
                }
            ]
        },
        {
            "date": "2013-05-04T18:15:00",
            "episode": 5,
            "score": 6.9708424182,
            "torrents": [
                {
                    "additional_info": "[480p]",
                    "download_count": 1,
                    "filename": "[HorribleSubs] Namiuchigiwa no Muromi-san - 05 [480p].mkv",
                    "group": "HorribleSubs",
                    "hash": "",
                    "url": "http://www.nyaa.eu/?page=download&tid=430367",
                    "version": 1
                },
                {
                    "additional_info": "[720p]",
                    "download_count": 7,
                    "filename": "[HorribleSubs] Namiuchigiwa no Muromi-san - 05 [720p].mkv",
                    "group": "HorribleSubs",
                    "hash": "",
                    "url": "http://www.nyaa.eu/?page=download&tid=430368",
                    "version": 1
                },
                {
                    "additional_info": "[1080p]",
                    "download_count": 2,
                    "filename": "[HorribleSubs] Namiuchigiwa no Muromi-san - 05 [1080p].mkv",
                    "group": "HorribleSubs",
                    "hash": "",
                    "url": "http://www.nyaa.eu/?page=download&tid=430369",
                    "version": 1
                },
                {
                    "additional_info": "",
                    "download_count": 3,
                    "filename": "[Vivid] Namiuchigiwa no Muromi-san - 05 [8D4E961A].mkv",
                    "group": "Vivid",
                    "hash": "8D4E961A",
                    "url": "http://www.nyaa.eu/?page=download&tid=430525",
                    "version": 1
                }
            ]
        },
        {
            "date": "2013-05-11T18:15:00",
            "episode": 6,
            "score": 6.9087547336,
            "torrents": [
                {
                    "additional_info": "[480p]",
                    "download_count": 0,
                    "filename": "[HorribleSubs] Namiuchigiwa no Muromi-san - 06 [480p].mkv",
                    "group": "HorribleSubs",
                    "hash": "",
                    "url": "http://www.nyaa.eu/?page=download&tid=432630",
                    "version": 1
                },
                {
                    "additional_info": "[720p]",
                    "download_count": 7,
                    "filename": "[HorribleSubs] Namiuchigiwa no Muromi-san - 06 [720p].mkv",
                    "group": "HorribleSubs",
                    "hash": "",
                    "url": "http://www.nyaa.eu/?page=download&tid=432631",
                    "version": 1
                },
                {
                    "additional_info": "[1080p]",
                    "download_count": 1,
                    "filename": "[HorribleSubs] Namiuchigiwa no Muromi-san - 06 [1080p].mkv",
                    "group": "HorribleSubs",
                    "hash": "",
                    "url": "http://www.nyaa.eu/?page=download&tid=432632",
                    "version": 1
                },
                {
                    "additional_info": "",
                    "download_count": 1,
                    "filename": "[Vivid] Namiuchigiwa no Muromi-san - 06 [8277C4C1].mkv",
                    "group": "Vivid",
                    "hash": "8277C4C1",
                    "url": "http://www.nyaa.eu/?page=download&tid=432790",
                    "version": 1
                }
            ]
        },
        {
            "date": "2013-05-18T18:15:00",
            "episode": 7,
            "score": 6.9388560886,
            "torrents": [
                {
                    "additional_info": "[480p]",
                    "download_count": 0,
                    "filename": "[HorribleSubs] Namiuchigiwa no Muromi-san - 07 [480p].mkv",
                    "group": "HorribleSubs",
                    "hash": "",
                    "url": "http://www.nyaa.eu/?page=download&tid=434794",
                    "version": 1
                },
                {
                    "additional_info": "[720p]",
                    "download_count": 6,
                    "filename": "[HorribleSubs] Namiuchigiwa no Muromi-san - 07 [720p].mkv",
                    "group": "HorribleSubs",
                    "hash": "",
                    "url": "http://www.nyaa.eu/?page=download&tid=434795",
                    "version": 1
                },
                {
                    "additional_info": "[1080p]",
                    "download_count": 2,
                    "filename": "[HorribleSubs] Namiuchigiwa no Muromi-san - 07 [1080p].mkv",
                    "group": "HorribleSubs",
                    "hash": "",
                    "url": "http://www.nyaa.eu/?page=download&tid=434797",
                    "version": 1
                },
                {
                    "additional_info": "",
                    "download_count": 1,
                    "filename": "[Vivid] Namiuchigiwa no Muromi-san - 07 [45761B5F].mkv",
                    "group": "Vivid",
                    "hash": "45761B5F",
                    "url": "http://www.nyaa.eu/?page=download&tid=434938",
                    "version": 1
                }
            ]
        },
        {
            "date": "2013-05-25T18:15:00",
            "episode": 8,
            "score": 6.9727228963,
            "torrents": [
                {
                    "additional_info": "[480p]",
                    "download_count": 0,
                    "filename": "[HorribleSubs] Namiuchigiwa no Muromi-san - 08 [480p].mkv",
                    "group": "HorribleSubs",
                    "hash": "",
                    "url": "http://www.nyaa.eu/?page=download&tid=436906",
                    "version": 1
                },
                {
                    "additional_info": "[1080p]",
                    "download_count": 1,
                    "filename": "[HorribleSubs] Namiuchigiwa no Muromi-san - 08 [1080p].mkv",
                    "group": "HorribleSubs",
                    "hash": "",
                    "url": "http://www.nyaa.eu/?page=download&tid=436907",
                    "version": 1
                },
                {
                    "additional_info": "[720p]",
                    "download_count": 7,
                    "filename": "[HorribleSubs] Namiuchigiwa no Muromi-san - 08 [720p].mkv",
                    "group": "HorribleSubs",
                    "hash": "",
                    "url": "http://www.nyaa.eu/?page=download&tid=436908",
                    "version": 1
                },
                {
                    "additional_info": "",
                    "download_count": 1,
                    "filename": "[Vivid] Namiuchigiwa no Muromi-san - 08 [091B7E12].mkv",
                    "group": "Vivid",
                    "hash": "091B7E12",
                    "url": "http://www.nyaa.eu/?page=download&tid=437021",
                    "version": 1
                }
            ]
        },
        {
            "date": "2013-06-01T18:15:00",
            "episode": 9,
            "score": 6.9833097015,
            "torrents": [
                {
                    "additional_info": "[480p]",
                    "download_count": 2,
                    "filename": "[HorribleSubs] Namiuchigiwa no Muromi-san - 09 [480p].mkv",
                    "group": "HorribleSubs",
                    "hash": "",
                    "url": "http://www.nyaa.eu/?page=download&tid=439050",
                    "version": 1
                },
                {
                    "additional_info": "[720p]",
                    "download_count": 4,
                    "filename": "[HorribleSubs] Namiuchigiwa no Muromi-san - 09 [720p].mkv",
                    "group": "HorribleSubs",
                    "hash": "",
                    "url": "http://www.nyaa.eu/?page=download&tid=439054",
                    "version": 1
                },
                {
                    "additional_info": "[1080p]",
                    "download_count": 1,
                    "filename": "[HorribleSubs] Namiuchigiwa no Muromi-san - 09 [1080p].mkv",
                    "group": "HorribleSubs",
                    "hash": "",
                    "url": "http://www.nyaa.eu/?page=download&tid=439056",
                    "version": 1
                },
                {
                    "additional_info": "",
                    "download_count": 0,
                    "filename": "[Vivid] Namiuchigiwa no Muromi-san - 09 [117A4CB5].mkv",
                    "group": "Vivid",
                    "hash": "117A4CB5",
                    "url": "http://www.nyaa.eu/?page=download&tid=439159",
                    "version": 1
                }
            ]
        },
        {
            "date": "2013-06-08T18:15:00",
            "episode": 10,
            "score": 7.0017247511,
            "torrents": [
                {
                    "additional_info": "[480p]",
                    "download_count": 0,
                    "filename": "[HorribleSubs] Namiuchigiwa no Muromi-san - 10 [480p].mkv",
                    "group": "HorribleSubs",
                    "hash": "",
                    "url": "http://www.nyaa.eu/?page=download&tid=441204",
                    "version": 1
                },
                {
                    "additional_info": "[720p]",
                    "download_count": 4,
                    "filename": "[HorribleSubs] Namiuchigiwa no Muromi-san - 10 [720p].mkv",
                    "group": "HorribleSubs",
                    "hash": "",
                    "url": "http://www.nyaa.eu/?page=download&tid=441205",
                    "version": 1
                },
                {
                    "additional_info": "[1080p]",
                    "download_count": 1,
                    "filename": "[HorribleSubs] Namiuchigiwa no Muromi-san - 10 [1080p].mkv",
                    "group": "HorribleSubs",
                    "hash": "",
                    "url": "http://www.nyaa.eu/?page=download&tid=441206",
                    "version": 1
                },
                {
                    "additional_info": "",
                    "download_count": 1,
                    "filename": "[Vivid] Namiuchigiwa no Muromi-san - 10 [58CF780E].mkv",
                    "group": "Vivid",
                    "hash": "58CF780E",
                    "url": "http://www.nyaa.eu/?page=download&tid=441343",
                    "version": 1
                }
            ]
        },
        {
            "date": "2013-06-15T18:15:00",
            "episode": 11,
            "score": 7.0153814574,
            "torrents": [
                {
                    "additional_info": "[480p]",
                    "download_count": 0,
                    "filename": "[HorribleSubs] Namiuchigiwa no Muromi-san - 11 [480p].mkv",
                    "group": "HorribleSubs",
                    "hash": "",
                    "url": "http://www.nyaa.eu/?page=download&tid=443305",
                    "version": 1
                },
                {
                    "additional_info": "[720p]",
                    "download_count": 5,
                    "filename": "[HorribleSubs] Namiuchigiwa no Muromi-san - 11 [720p].mkv",
                    "group": "HorribleSubs",
                    "hash": "",
                    "url": "http://www.nyaa.eu/?page=download&tid=443307",
                    "version": 1
                },
                {
                    "additional_info": "[1080p]",
                    "download_count": 1,
                    "filename": "[HorribleSubs] Namiuchigiwa no Muromi-san - 11 [1080p].mkv",
                    "group": "HorribleSubs",
                    "hash": "",
                    "url": "http://www.nyaa.eu/?page=download&tid=443309",
                    "version": 1
                },
                {
                    "additional_info": "",
                    "download_count": 1,
                    "filename": "[Vivid] Namiuchigiwa no Muromi-san - 11 [1544A55D].mkv",
                    "group": "Vivid",
                    "hash": "1544A55D",
                    "url": "http://www.nyaa.eu/?page=download&tid=443421",
                    "version": 1
                }
            ]
        },
        {
            "date": "2013-06-22T18:15:00",
            "episode": 12,
            "score": 7.0146782748,
            "torrents": [
                {
                    "additional_info": "[480p]",
                    "download_count": 0,
                    "filename": "[HorribleSubs] Namiuchigiwa no Muromi-san - 12 [480p].mkv",
                    "group": "HorribleSubs",
                    "hash": "",
                    "url": "http://www.nyaa.eu/?page=download&tid=445276",
                    "version": 1
                },
                {
                    "additional_info": "[1080p]",
                    "download_count": 1,
                    "filename": "[HorribleSubs] Namiuchigiwa no Muromi-san - 12 [1080p].mkv",
                    "group": "HorribleSubs",
                    "hash": "",
                    "url": "http://www.nyaa.eu/?page=download&tid=445277",
                    "version": 1
                },
                {
                    "additional_info": "[720p]",
                    "download_count": 3,
                    "filename": "[HorribleSubs] Namiuchigiwa no Muromi-san - 12 [720p].mkv",
                    "group": "HorribleSubs",
                    "hash": "",
                    "url": "http://www.nyaa.eu/?page=download&tid=445278",
                    "version": 1
                },
                {
                    "additional_info": "",
                    "download_count": 1,
                    "filename": "[Vivid] Namiuchigiwa no Muromi-san - 12 [999BC8B2].mkv",
                    "group": "Vivid",
                    "hash": "999BC8B2",
                    "url": "http://www.nyaa.eu/?page=download&tid=445399",
                    "version": 1
                }
            ]
        },
        {
            "date": "2013-06-29T18:15:00",
            "episode": 13,
            "score": 7.171260686,
            "torrents": [
                {
                    "additional_info": "",
                    "download_count": 0,
                    "filename": "[Vivid] Namiuchigiwa no Muromi-san - 13 [156C1699].mkv",
                    "group": "Vivid",
                    "hash": "156C1699",
                    "url": "http://www.nyaa.eu/?page=download&tid=447743",
                    "version": 1
                },
                {
                    "additional_info": "[480p]",
                    "download_count": 0,
                    "filename": "[HorribleSubs] Namiuchigiwa no Muromi-san - 13 [480p].mkv",
                    "group": "HorribleSubs",
                    "hash": "",
                    "url": "http://www.nyaa.eu/?page=download&tid=447604",
                    "version": 1
                },
                {
                    "additional_info": "[720p]",
                    "download_count": 4,
                    "filename": "[HorribleSubs] Namiuchigiwa no Muromi-san - 13 [720p].mkv",
                    "group": "HorribleSubs",
                    "hash": "",
                    "url": "http://www.nyaa.eu/?page=download&tid=447599",
                    "version": 1
                },
                {
                    "additional_info": "[1080p]",
                    "download_count": 0,
                    "filename": "[HorribleSubs] Namiuchigiwa no Muromi-san - 13 [1080p].mkv",
                    "group": "HorribleSubs",
                    "hash": "",
                    "url": "http://www.nyaa.eu/?page=download&tid=447603",
                    "version": 1
                }
            ]
        }
    ],
    "episodes_count": 13,
    "episodes_length": 5,
    "external_sites": {
        "anidb": 9479,
        "ann": 14999,
        "mal": 16910,
        "schedule": null
    },
    "images": [],
    "plots": [
        {
            "content": "Mukoujima Takurou is a lonely teenager who spends his time fishing at the pier and, to his incredible surprise, fishes up Muromi, a mermaid. Muromi first off doesn't realize she's a mermaid until she meets Takurou. Not only that, she is incredibly dense and crazy and has a drinking problem to top it off. Now every time Takurou goes fishing, Muromi appears and makes life interesting for him.",
            "type": "mal"
        },
        {
            "content": "Mukoujima Takurou is a lonely teenager who spends his time fishing at the pier and, to his incredible surprise, fishes up Muromi, a mermaid. Muromi first off doesn't realize she's a mermaid until she meets Takurou. Not only that, she is incredibly dense and crazy and has a drinking problem to top it off. Now every time Takurou goes fishing, Muromi appears and makes life interesting for him.Source: Mangaupdates",
            "type": "anidb"
        },
        {
            "content": "Takur\u014d Muk\u014djima is an angler boy. He often lands a ningyo (Japanese mermaid) Muromi-san and has a chat with her and her strange friends.",
            "type": "wiki"
        },
        {
            "content": "One day, Takur\u014d was fishing at the pier as usual, when he caught the big one- a mermaid. However, contrary to her legendary appearance, she's head-over-heels for \"Takkun\", uses a shell-phone, and is instinctively afraid of birds and seals due to their love of fish. Since the time he met Muromi, he's met Leviathan, a yeti, a harpie, a kappa, and more. It seems his relationship with the spunky mermaid gets weirder by the day.",
            "type": "ann"
        }
    ],
    "ranks": [
        {
            "count": 3492,
            "date": "2013-07-01T04:31:04",
            "score": 7.2,
            "type": "mal"
        },
        {
            "count": 155,
            "date": "2013-07-01T04:31:04",
            "score": 6.87,
            "type": "anidb"
        },
        {
            "count": 143,
            "date": "2013-07-01T04:31:04",
            "score": 6.796,
            "type": "ann"
        }
    ],
    "season": {
        "quarter": 2,
        "year": 2013
    },
    "sequel": false,
    "sequel_parent": "",
    "title": "Namiuchigiwa no Muromi-san"
}